CHANGELOG.md
env_var/__init__.py
env_var/_transformers/date.py
env_var/_transformers/numeric.py
env_var/_transformers/string_validators.py
env_var/env.py
env_var/errors.py
env_var-1.0.1.dist-info/LICENSE
env_var-1.0.1.dist-info/WHEEL
env_var-1.0.1.dist-info/METADATA
env_var-1.0.1.dist-info/RECORD
