Metadata-Version: 2.1
Name: env-var
Version: 1.0.1
Summary: simple utility to parse and validate environment variables
Home-page: https://github.com/seba-ban/env-var
License: MIT
Keywords: environment,env-var
Author: Sebastian Banaszkiewicz
Author-email: banaszkiewicz.sebastian@gmail.com
Requires-Python: >=3.8,<4.0
Classifier: License :: OSI Approved :: MIT License
Classifier: Programming Language :: Python :: 3
Classifier: Programming Language :: Python :: 3.10
Classifier: Programming Language :: Python :: 3.8
Classifier: Programming Language :: Python :: 3.9
Requires-Dist: isoduration (>=20.11.0,<21.0.0)
Requires-Dist: python-dateutil (>=2.8.2,<3.0.0)
Requires-Dist: rfc3339-validator (>=0.1.4,<0.2.0)
Requires-Dist: rfc3986-validator (>=0.1.1,<0.2.0)
Requires-Dist: validators (>=0.18.2,<0.19.0)
Project-URL: Documentation, https://env-var.readthedocs.io
Project-URL: Repository, https://github.com/seba-ban/env-var
